odoo/addons/component/README.rst
odoo/addons/component/__init__.py
odoo/addons/component/__manifest__.py
odoo/addons/component/builder.py
odoo/addons/component/core.py
odoo/addons/component/exception.py
odoo/addons/component/components/__init__.py
odoo/addons/component/components/base.py
odoo/addons/component/i18n/am.po
odoo/addons/component/i18n/ca.po
odoo/addons/component/i18n/component.pot
odoo/addons/component/i18n/de.po
odoo/addons/component/i18n/el_GR.po
odoo/addons/component/i18n/es.po
odoo/addons/component/i18n/es_ES.po
odoo/addons/component/i18n/fi.po
odoo/addons/component/i18n/fr.po
odoo/addons/component/i18n/gl.po
odoo/addons/component/i18n/it.po
odoo/addons/component/i18n/pt.po
odoo/addons/component/i18n/pt_BR.po
odoo/addons/component/i18n/pt_PT.po
odoo/addons/component/i18n/sl.po
odoo/addons/component/i18n/tr.po
odoo/addons/component/i18n/zh_CN.po
odoo/addons/component/models/__init__.py
odoo/addons/component/models/collection.py
odoo/addons/component/readme/CONTRIBUTORS.rst
odoo/addons/component/readme/DESCRIPTION.rst
odoo/addons/component/readme/HISTORY.rst
odoo/addons/component/readme/USAGE.rst
odoo/addons/component/static/description/icon.png
odoo/addons/component/static/description/index.html
odoo/addons/component/tests/__init__.py
odoo/addons/component/tests/common.py
odoo/addons/component/tests/test_build_component.py
odoo/addons/component/tests/test_component.py
odoo/addons/component/tests/test_lookup.py
odoo/addons/component/tests/test_work_on.py
odoo12_addon_component-12.0.1.1.1.dist-info/METADATA
odoo12_addon_component-12.0.1.1.1.dist-info/WHEEL
odoo12_addon_component-12.0.1.1.1.dist-info/top_level.txt
odoo12_addon_component-12.0.1.1.1.dist-info/RECORD
