Metadata-Version: 2.1
Name: odoo12-addon-component
Version: 12.0.1.1.1
Summary: Add capabilities to register and use decoupled components, as an alternative to model classes
Home-page: https://github.com/OCA/connector
Author: Camptocamp,Odoo Community Association (OCA)
Author-email: support@odoo-community.org
License: LGPL-3
Platform: UNKNOWN
Classifier: Programming Language :: Python
Classifier: Framework :: Odoo
Classifier: Framework :: Odoo :: 12.0
Classifier: License :: OSI Approved :: GNU Lesser General Public License v3 (LGPLv3)
Classifier: Development Status :: 5 - Production/Stable
Requires-Python: >=3.5
Requires-Dist: cachetools
Requires-Dist: odoo (<12.1dev,>=12.0a)
Requires-Dist: cachetools (>=2.0.1)
